mcp_server_schedule_manage.py
mcp_server_schedule_manage-0.1.4.dist-info/METADATA
mcp_server_schedule_manage-0.1.4.dist-info/WHEEL
mcp_server_schedule_manage-0.1.4.dist-info/entry_points.txt
mcp_server_schedule_manage-0.1.4.dist-info/RECORD
