Metadata-Version: 2.4
Name: mcp-server-schedule-manage
Version: 0.1.4
Summary: A simple MCP schedule manage server
Author-email: hechangtian <15993091621@163.com>
Requires-Python: >=3.10
